tresearcher/__init__.py
tresearcher/graph/__init__.py
tresearcher/graph/graph.py
tresearcher/researcher/__init__.py
tresearcher/researcher/assist.py
tresearcher/researcher/experiment.py
tresearcher/researcher/glob.py
tresearcher/researcher/metric.py
tresearcher/researcher/records.py
tresearcher/researcher/results.py
tresearcher/researcher/run.py
tresearcher/researcher/test_records.py
tresearcher/researcher/test_results.py
tresearcher/tabular/__init__.py
tresearcher/tabular/experiment.py
tresearcher/tabular/glob.py
tresearcher/tabular/load.py
tresearcher/tabular/metrics.py
tresearcher/tabular/models.py
tresearcher/tabular/pipeline.py
tresearcher/tabular/split.py
tresearcher-0.0.2.dist-info/LICENSE
tresearcher-0.0.2.dist-info/METADATA
tresearcher-0.0.2.dist-info/WHEEL
tresearcher-0.0.2.dist-info/top_level.txt
tresearcher-0.0.2.dist-info/RECORD
